{"64060":{"channel":"K0v3rjCcK3Oixrld-oQ4PypqHHLv46mGFLirNnGs","start":"1673430300","end":"1673431200","title":"Basketbal: NBA Samenvatting : NBA: Warriors vs Suns ","program_id":"EJ4hV0wud_dWFgWr6xrPjWJMxokPA4GAIGMMmS4x","date":"","icon":"https:\/\/m7be2.solocoo.tv\/m7be2iphone\/mmchan\/mpimages\/260x145\/K6Ac8PmA93unnOIliH1RTw.jpg","description":"","category":""},"66118":{"channel":"Wje__DuX-WsldSDSS525kQZShS_jyyxLQWsiK50d","start":"1673437500","end":"1673438400","title":"Basketbal: NBA Samenvatting : NBA: Warriors vs Suns ","program_id":"T4sCsygPcO12om-XMpEOgiIm8y9_kvqXDGSLK6M7","date":"","icon":"https:\/\/m7be2.solocoo.tv\/m7be2iphone\/mmchan\/mpimages\/260x145\/K6Ac8PmA93unnOIliH1RTw.jpg","description":"","category":""},"64133":{"channel":"KtsZ5_fMe5XExFDbvsVb0ouFnopX0D8zdKXjBEFq","start":"1673442000","end":"1673442900","title":"Basketbal: NBA Samenvatting : NBA: Warriors vs Suns ","program_id":"i6vuHeXHJhE2JGAizwWycTzZoa55753ih0yKYYWp","date":"","icon":"https:\/\/m7be2.solocoo.tv\/m7be2iphone\/mmchan\/mpimages\/260x145\/K6Ac8PmA93unnOIliH1RTw.jpg","description":"","category":""}}