{"10589721":{"channel":"lgi-nl-prod-master:NL_000066_019291","start":"1627338300","end":"1627341300","first":"W","idtitle":"WRITTENINBLOOD","title":"Written In Blood","program_id":"crid:~~2F~~2Fgn.tv~~2F14350467~~2FSH027372890000~~2F75763029,imi:c2e45d4241e897135892d473b218e4e767ba37f3","date":"","icon":"https:\/\/staticqbr-nl-prod.prod.cdn.dmdsdp.com\/image-service\/ImagesEPG\/EventImages\/p14350467_b_v8_aa.jpg","description":"Crime novelist Simon Toyne examines some of the darkest real-life crime stories. He investigates the similarities between the works of famous writers and the grim realities of true crime.","category":"Documentaire, Misdaad"},"10590670":{"channel":"lgi-nl-prod-master:NL_000066_019291","start":"1627341300","end":"1627342800","first":"J","idtitle":"JUDGEJUDY","title":"Judge Judy","program_id":"crid:~~2F~~2Fgn.tv~~2F8706971~~2FEP012603133386,imi:718b44607d2af10b1c139eb917bcd94450b41598","date":"2011","icon":"https:\/\/staticqbr-nl-prod.prod.cdn.dmdsdp.com\/image-service\/ImagesEPG\/EventImages\/p9199058_b_v12_aa.jpg","description":"A young man with two DUIs, who is trying to stay sober, breaks up with his new, live-in girlfriend but suggests that she stay in the other bedroom; he sues her for unpaid rent.","category":"Reality, Recht"},"10590759":{"channel":"lgi-nl-prod-master:NL_000066_019291","start":"1627342800","end":"1627345800","first":"C","idtitle":"CHEATERS","title":"Cheaters","program_id":"crid:~~2F~~2Fgn.tv~~2F2435949~~2FEP012731240315,imi:bfe175d74405eced4d742532dbd1817826bed203","date":"2008","icon":"https:\/\/staticqbr-nl-prod.prod.cdn.dmdsdp.com\/image-service\/ImagesEPG\/EventImages\/p185490_b_v8_aj.jpg","description":"Pablo is suspicious of wife Patsy's social life, especially after finding hotel receipts in her purse. Lashonda grows tired of partner Glenn's duplicity.","category":"Reality"},"10591699":{"channel":"lgi-nl-prod-master:NL_000066_019291","start":"1627345800","end":"1627348800","first":"W","idtitle":"WORLDSMOSTEVILKILLERS","title":"World's Most Evil Killers","program_id":"crid:~~2F~~2Fgn.tv~~2F17969781~~2FEP026904340042,imi:188c974ba1cc374660696a3ced7a81a4171419da","date":"2020","icon":"https:\/\/staticqbr-nl-prod.prod.cdn.dmdsdp.com\/image-service\/ImagesEPG\/EventImages\/p17233730_b_v12_aa.jpg","description":"Looking at the life and horrifying crimes of Angel Maturino Res\u00e9ndiz, also known as the Railroad Killer as most of his crimes were committed near railways as he travelled across the United States.","category":"Documentaire, Misdaad"},"10592640":{"channel":"lgi-nl-prod-master:NL_000066_019291","start":"1627348800","end":"1627350000","first":"J","idtitle":"JUDGEJUDY","title":"Judge Judy","program_id":"crid:~~2F~~2Fgn.tv~~2F9170421~~2FEP012603131297,imi:f164dd1013b5e8d1225dc3422e4c7db2d89601f7","date":"2012","icon":"https:\/\/staticqbr-nl-prod.prod.cdn.dmdsdp.com\/image-service\/ImagesEPG\/EventImages\/p9108213_b_v12_aa.jpg","description":"A tenant accuses his landlord of breaking into his home and injuring his dog during a dispute. Then, a teen sues for emotional distress after being accused of injuring a classmate with a box cutter.","category":"Reality, Recht"},"10592722":{"channel":"lgi-nl-prod-master:NL_000066_019291","start":"1627350000","end":"1627351500","first":"J","idtitle":"JUDGEJUDY","title":"Judge Judy","program_id":"crid:~~2F~~2Fgn.tv~~2F9170412~~2FEP012603131298,imi:021ac05befc1716d326fc5726f942984d62e1d0b","date":"2012","icon":"https:\/\/staticqbr-nl-prod.prod.cdn.dmdsdp.com\/image-service\/ImagesEPG\/EventImages\/p9108213_b_v12_aa.jpg","description":"A man refuses to repay his mother-in-law for a new heating unit. Then, former classmates dispute details of drunken rage and vandalism to a truck.","category":"Reality, Recht"},"10592837":{"channel":"lgi-nl-prod-master:NL_000066_019291","start":"1627351500","end":"1627352700","first":"J","idtitle":"JUDGEJUDY","title":"Judge Judy","program_id":"crid:~~2F~~2Fgn.tv~~2F9170419~~2FEP012603131299,imi:db1ef0c99b3a22862bd9431067268e0761313629","date":"2012","icon":"https:\/\/staticqbr-nl-prod.prod.cdn.dmdsdp.com\/image-service\/ImagesEPG\/EventImages\/p9108213_b_v12_aa.jpg","description":"A man sues his ex for half of the cost of a dog and its obedience training. Then, a woman sues her friend's estranged wife for a computer monitor and harassment and a plaintiff sues his nephew's father for medical bills and living expenses.","category":"Reality, Recht"},"10593646":{"channel":"lgi-nl-prod-master:NL_000066_019291","start":"1627352700","end":"1627355400","first":"S","idtitle":"SOMETHINGSKILLINGME","title":"Something's Killing Me","program_id":"crid:~~2F~~2Fgn.tv~~2F17483203~~2FEP030640520016,imi:6a32197be63af611fa8ce4a2d9b2b71f62864cd2","date":"2019","icon":"https:\/\/staticqbr-nl-prod.prod.cdn.dmdsdp.com\/image-service\/ImagesEPG\/EventImages\/p17462817_b_v12_aa.jpg","description":"Dr. Bill Lidner collapses after returning home from a family trip overseas; his daughters find him bleeding; they don't know it, but it's the first sign that something's very wrong.","category":"Documentaire, Medisch, Gezondheid"},"10593826":{"channel":"lgi-nl-prod-master:NL_000066_019291","start":"1627355400","end":"1627356900","first":"O","idtitle":"OPERATIONREPO","title":"Operation Repo","program_id":"crid:~~2F~~2Fgn.tv~~2F196625~~2FSH012612590000~~2F75763037,imi:882b78cfe5275adb8acffc14d7e5dc65c4900f5e","date":"","icon":"https:\/\/staticqbr-nl-prod.prod.cdn.dmdsdp.com\/image-service\/ImagesEPG\/EventImages\/p196625_b_v7_am.jpg","description":"Viewers get to ride along with a team of highly-trained professionals from California's San Fernando Valley as they repossess cars ... no matter how angry the owners may get. The stories depicted are based on real events.","category":"Reality"},"10594690":{"channel":"lgi-nl-prod-master:NL_000066_019291","start":"1627356900","end":"1627358400","first":"O","idtitle":"OPERATIONREPO","title":"Operation Repo","program_id":"crid:~~2F~~2Fgn.tv~~2F196625~~2FSH012612590000~~2F75763038,imi:ed2c6700bdb2110e557a92bf3796e87490e0ff84","date":"","icon":"https:\/\/staticqbr-nl-prod.prod.cdn.dmdsdp.com\/image-service\/ImagesEPG\/EventImages\/p196625_b_v7_am.jpg","description":"Viewers get to ride along with a team of highly-trained professionals from California's San Fernando Valley as they repossess cars ... no matter how angry the owners may get. The stories depicted are based on real events.","category":"Reality"},"10594783":{"channel":"lgi-nl-prod-master:NL_000066_019291","start":"1627358400","end":"1627359900","first":"J","idtitle":"JUDGEJUDY","title":"Judge Judy","program_id":"crid:~~2F~~2Fgn.tv~~2F9237785~~2FEP012603131374,imi:62d5116cc6c0be47bae5fcf0ac84eba23933e4f1","date":"2012","icon":"https:\/\/staticqbr-nl-prod.prod.cdn.dmdsdp.com\/image-service\/ImagesEPG\/EventImages\/p9108213_b_v12_aa.jpg","description":"After a man becomes romantically involved with his child's teacher, she accuses him of giving her a disease and mistreating his daughter.","category":"Reality, Recht"},"10595636":{"channel":"lgi-nl-prod-master:NL_000066_019291","start":"1627359900","end":"1627361400","first":"J","idtitle":"JUDGEJUDY","title":"Judge Judy","program_id":"crid:~~2F~~2Fgn.tv~~2F9148181~~2FEP012603131382,imi:91b36bbad51a272e6eb74ec6402238060787d8ee","date":"2012","icon":"https:\/\/staticqbr-nl-prod.prod.cdn.dmdsdp.com\/image-service\/ImagesEPG\/EventImages\/p9108213_b_v12_aa.jpg","description":"A grandmother accuses her daughter-in-law of bringing gangsters to shoot her after a domestic dispute.","category":"Reality, Recht"},"10595727":{"channel":"lgi-nl-prod-master:NL_000066_019291","start":"1627361400","end":"1627364400","first":"E","idtitle":"EXTREMESALVAGESQUAD","title":"Extreme Salvage Squad","program_id":"crid:~~2F~~2Fgn.tv~~2F15897481~~2FEP032189780005,imi:7f03e243d6a711d2f1f224a7166a6ef78cdd43c2","date":"2019","icon":"https:\/\/staticqbr-nl-prod.prod.cdn.dmdsdp.com\/image-service\/ImagesEPG\/EventImages\/p15774214_b_v11_ad.jpg","description":"The team head out during low tide to attempt the removal of a damaged pontoon, starting by pumping out the sand that is weighing it down.","category":"Reality, Documentaire"},"10596717":{"channel":"lgi-nl-prod-master:NL_000066_019291","start":"1627364400","end":"1627367400","first":"D","idtitle":"DOGANDBETHONTHEHUNT","title":"Dog and Beth: On the Hunt","program_id":"crid:~~2F~~2Fgn.tv~~2F9494937~~2FSH017801230000~~2F75762960,imi:a2866f6bdc99d88328f8fa207b06e21884e39db4","date":"","icon":"https:\/\/staticqbr-nl-prod.prod.cdn.dmdsdp.com\/image-service\/ImagesEPG\/EventImages\/p9494937_b_v12_aw.jpg","description":"They say, `you can't teach an old dog new tricks', but nobody has said anything about being unable to teach a bounty-hunting Dog new tricks. Which is good because after an eight-season run on A&E, Duane `Dog' Chapman brings his people-tracking skills to a new network, along with wife Beth and their son, Leland. But this time the Chapmans aren't searching for fugitives on their home turf of Hawaii. Instead, they travel to a different city each week and work with the local bondsman offices and bounty hunters, using their years of experience in the business to assist the local agents. The Chapmans motivate and inspire the local bounty hunters while training them how to use high-tech tracking devices and showing them new techniques they can use in finding fugitives.","category":"Reality, Misdaad"},"10597650":{"channel":"lgi-nl-prod-master:NL_000066_019291","start":"1627367400","end":"1627368900","first":"C","idtitle":"CLOSECALLSONCAMERA","title":"Close Calls: On Camera","program_id":"crid:~~2F~~2Fgn.tv~~2F15869635~~2FEP020253820089,imi:9721c1db51e33070fdd4a5760d4ea9fe62f214dd","date":"2018","icon":"https:\/\/staticqbr-nl-prod.prod.cdn.dmdsdp.com\/image-service\/ImagesEPG\/EventImages\/p15506480_b_v8_ab.jpg","description":"Presenter Nick Knowles tells the emotional story of a dad and his 12-year-old daughter lost overnight on a glacier in freezing temperatures. Plus, a man wakes to find his canal boat is sinking when the bank is breached downstream.","category":"Documentaire, Reality"},"10597724":{"channel":"lgi-nl-prod-master:NL_000066_019291","start":"1627368900","end":"1627370400","first":"O","idtitle":"OPERATIONREPO","title":"Operation Repo","program_id":"crid:~~2F~~2Fgn.tv~~2F196625~~2FSH012612590000~~2F75762962,imi:a04bd319125a9d403fe1ec883eae2fd89886391c","date":"","icon":"https:\/\/staticqbr-nl-prod.prod.cdn.dmdsdp.com\/image-service\/ImagesEPG\/EventImages\/p196625_b_v7_am.jpg","description":"Viewers get to ride along with a team of highly-trained professionals from California's San Fernando Valley as they repossess cars ... no matter how angry the owners may get. The stories depicted are based on real events.","category":"Reality"},"10597830":{"channel":"lgi-nl-prod-master:NL_000066_019291","start":"1627370400","end":"1627371900","first":"O","idtitle":"OPERATIONREPO","title":"Operation Repo","program_id":"crid:~~2F~~2Fgn.tv~~2F196625~~2FSH012612590000~~2F75762963,imi:d7e90196a86a59aa6c350e631ee25fbd1f74ec73","date":"","icon":"https:\/\/staticqbr-nl-prod.prod.cdn.dmdsdp.com\/image-service\/ImagesEPG\/EventImages\/p196625_b_v7_am.jpg","description":"Viewers get to ride along with a team of highly-trained professionals from California's San Fernando Valley as they repossess cars ... no matter how angry the owners may get. The stories depicted are based on real events.","category":"Reality"},"10598665":{"channel":"lgi-nl-prod-master:NL_000066_019291","start":"1627371900","end":"1627374900","first":"H","idtitle":"HAUNTEDCASEFILES","title":"Haunted Case Files","program_id":"crid:~~2F~~2Fgn.tv~~2F15519807~~2FEP026159030001,imi:0245af902816a6c0bab2d90cd461972a5983d8b7","date":"2018","icon":"https:\/\/staticqbr-nl-prod.prod.cdn.dmdsdp.com\/image-service\/ImagesEPG\/EventImages\/p15782324_b_v12_ab.jpg","description":"Michelle Desrochers' dream trip to Transylvania turns into a nightmare, while in New York, paranormal investigators are attacked by a dangerous entity stalking an old church.","category":"Documentaire, Paranormaal, Bloemlezing"},"10599610":{"channel":"lgi-nl-prod-master:NL_000066_019291","start":"1627374900","end":"1627376400","first":"J","idtitle":"JUDGEJUDY","title":"Judge Judy","program_id":"crid:~~2F~~2Fgn.tv~~2F10002688~~2FEP012603132192,imi:52d0b5f814ebd17bfc6cbceb1c32d627c06ea5af","date":"2013","icon":"https:\/\/staticqbr-nl-prod.prod.cdn.dmdsdp.com\/image-service\/ImagesEPG\/EventImages\/p9442556_b_v12_aa.jpg","description":"A plaintiff regrets helping out his daughter and son-in-law, who resist paying off their debt.","category":"Reality, Recht"},"10599684":{"channel":"lgi-nl-prod-master:NL_000066_019291","start":"1627376400","end":"1627377900","first":"J","idtitle":"JUDGEJUDY","title":"Judge Judy","program_id":"crid:~~2F~~2Fgn.tv~~2F9988720~~2FEP012603132193,imi:ccd9986399e21c0a971115fd5819f45615d4b07f","date":"2013","icon":"https:\/\/staticqbr-nl-prod.prod.cdn.dmdsdp.com\/image-service\/ImagesEPG\/EventImages\/p9442556_b_v12_aa.jpg","description":"A landlord says a couple with seven children and two animals left a house in shambles.","category":"Reality, Recht"},"10599764":{"channel":"lgi-nl-prod-master:NL_000066_019291","start":"1627377900","end":"1627379400","first":"J","idtitle":"JUDGEJUDY","title":"Judge Judy","program_id":"crid:~~2F~~2Fgn.tv~~2F9988718~~2FEP012603132194,imi:7965e7ec01cd8a761ad2a605a78402d0460a9e9d","date":"2013","icon":"https:\/\/staticqbr-nl-prod.prod.cdn.dmdsdp.com\/image-service\/ImagesEPG\/EventImages\/p9442556_b_v12_aa.jpg","description":"Accusations of breaking a lease; a 6-year-old denies crashing into a moving truck with his bicycle.","category":"Reality, Recht"},"10599830":{"channel":"lgi-nl-prod-master:NL_000066_019291","start":"1627379400","end":"1627380900","first":"O","idtitle":"OPERATIONREPO","title":"Operation Repo","program_id":"crid:~~2F~~2Fgn.tv~~2F196625~~2FSH012612590000~~2F75762968,imi:7cb214efaea6358c021e17d399da1ade3cb654bb","date":"","icon":"https:\/\/staticqbr-nl-prod.prod.cdn.dmdsdp.com\/image-service\/ImagesEPG\/EventImages\/p196625_b_v7_am.jpg","description":"Viewers get to ride along with a team of highly-trained professionals from California's San Fernando Valley as they repossess cars ... no matter how angry the owners may get. The stories depicted are based on real events.","category":"Reality"},"10600696":{"channel":"lgi-nl-prod-master:NL_000066_019291","start":"1627380900","end":"1627383900","first":"E","idtitle":"EXTREMESALVAGESQUAD","title":"Extreme Salvage Squad","program_id":"crid:~~2F~~2Fgn.tv~~2F15897481~~2FEP032189780005,imi:3a45d7319bc6b017aa778d7e4e773e0a14e174c0","date":"2019","icon":"https:\/\/staticqbr-nl-prod.prod.cdn.dmdsdp.com\/image-service\/ImagesEPG\/EventImages\/p15774214_b_v11_ad.jpg","description":"The team head out during low tide to attempt the removal of a damaged pontoon, starting by pumping out the sand that is weighing it down.","category":"Reality, Documentaire"},"10601558":{"channel":"lgi-nl-prod-master:NL_000066_019291","start":"1627383900","end":"1627386900","first":"S","idtitle":"SOMETHINGSKILLINGME","title":"Something's Killing Me","program_id":"crid:~~2F~~2Fgn.tv~~2F17462356~~2FEP030640520017,imi:df5237dd654f6ab72edf92e9b9a7a57b8295fdae","date":"2019","icon":"https:\/\/staticqbr-nl-prod.prod.cdn.dmdsdp.com\/image-service\/ImagesEPG\/EventImages\/p17462817_b_v12_aa.jpg","description":"Several doctors and CDC authorities spend months trying to figure out what California honeymooners, a surfer in Hawaii and a toddler in Tennessee have in common.","category":"Documentaire, Medisch, Gezondheid"},"10601711":{"channel":"lgi-nl-prod-master:NL_000066_019291","start":"1627386900","end":"1627388400","first":"C","idtitle":"CLOSECALLSONCAMERA","title":"Close Calls: On Camera","program_id":"crid:~~2F~~2Fgn.tv~~2F15869635~~2FEP020253820089,imi:82623a97f154136e2e3f12b911a9732fe50c1251","date":"2018","icon":"https:\/\/staticqbr-nl-prod.prod.cdn.dmdsdp.com\/image-service\/ImagesEPG\/EventImages\/p15506480_b_v8_ab.jpg","description":"Presenter Nick Knowles tells the emotional story of a dad and his 12-year-old daughter lost overnight on a glacier in freezing temperatures. Plus, a man wakes to find his canal boat is sinking when the bank is breached downstream.","category":"Documentaire, Reality"},"10602574":{"channel":"lgi-nl-prod-master:NL_000066_019291","start":"1627388400","end":"1627391400","first":"D","idtitle":"DOGANDBETHONTHEHUNT","title":"Dog and Beth: On the Hunt","program_id":"crid:~~2F~~2Fgn.tv~~2F9494937~~2FSH017801230000~~2F75762972,imi:f05f989361a4b2c613d8a82c281a4eb4f6c01596","date":"","icon":"https:\/\/staticqbr-nl-prod.prod.cdn.dmdsdp.com\/image-service\/ImagesEPG\/EventImages\/p9494937_b_v12_aw.jpg","description":"They say, `you can't teach an old dog new tricks', but nobody has said anything about being unable to teach a bounty-hunting Dog new tricks. Which is good because after an eight-season run on A&E, Duane `Dog' Chapman brings his people-tracking skills to a new network, along with wife Beth and their son, Leland. But this time the Chapmans aren't searching for fugitives on their home turf of Hawaii. Instead, they travel to a different city each week and work with the local bondsman offices and bounty hunters, using their years of experience in the business to assist the local agents. The Chapmans motivate and inspire the local bounty hunters while training them how to use high-tech tracking devices and showing them new techniques they can use in finding fugitives.","category":"Reality, Misdaad"},"10602752":{"channel":"lgi-nl-prod-master:NL_000066_019291","start":"1627391400","end":"1627392900","first":"J","idtitle":"JUDGEJUDY","title":"Judge Judy","program_id":"crid:~~2F~~2Fgn.tv~~2F8339942~~2FEP012603130133,imi:8b76fdfe438047d54622e8061d7713f560e00acb","date":"2010","icon":"https:\/\/staticqbr-nl-prod.prod.cdn.dmdsdp.com\/image-service\/ImagesEPG\/EventImages\/p9199058_b_v12_aa.jpg","description":"A couple who met in a rehab programme dispute their ill baby's exposure to marijuana smoke.","category":"Reality, Recht"},"10603581":{"channel":"lgi-nl-prod-master:NL_000066_019291","start":"1627392900","end":"1627394400","first":"J","idtitle":"JUDGEJUDY","title":"Judge Judy","program_id":"crid:~~2F~~2Fgn.tv~~2F8339985~~2FEP012603130134,imi:67cafafe0c88000eae427bd7262a1d2c454010a4","date":"2010","icon":"https:\/\/staticqbr-nl-prod.prod.cdn.dmdsdp.com\/image-service\/ImagesEPG\/EventImages\/p9199058_b_v12_aa.jpg","description":"A woman says her ex-neighbour assaulted her; he says she came after him with a bat.","category":"Reality, Recht"},"10603673":{"channel":"lgi-nl-prod-master:NL_000066_019291","start":"1627394400","end":"1627397400","first":"H","idtitle":"HAUNTEDCASEFILES","title":"Haunted Case Files","program_id":"crid:~~2F~~2Fgn.tv~~2F15519807~~2FEP026159030001,imi:6d360b52f766e7990bc6ae74c057f4220a50fdf0","date":"2018","icon":"https:\/\/staticqbr-nl-prod.prod.cdn.dmdsdp.com\/image-service\/ImagesEPG\/EventImages\/p15782324_b_v12_ab.jpg","description":"Michelle Desrochers' dream trip to Transylvania turns into a nightmare, while in New York, paranormal investigators are attacked by a dangerous entity stalking an old church.","category":"Documentaire, Paranormaal, Bloemlezing"},"10604593":{"channel":"lgi-nl-prod-master:NL_000066_019291","start":"1627397400","end":"1627398900","first":"O","idtitle":"OPERATIONREPO","title":"Operation Repo","program_id":"crid:~~2F~~2Fgn.tv~~2F196625~~2FSH012612590000~~2F75762976,imi:99e620c75e163be9d835d24dbc5d3df0fac20748","date":"","icon":"https:\/\/staticqbr-nl-prod.prod.cdn.dmdsdp.com\/image-service\/ImagesEPG\/EventImages\/p196625_b_v7_am.jpg","description":"Viewers get to ride along with a team of highly-trained professionals from California's San Fernando Valley as they repossess cars ... no matter how angry the owners may get. The stories depicted are based on real events.","category":"Reality"},"10604712":{"channel":"lgi-nl-prod-master:NL_000066_019291","start":"1627398900","end":"1627400400","first":"O","idtitle":"OPERATIONREPO","title":"Operation Repo","program_id":"crid:~~2F~~2Fgn.tv~~2F196625~~2FSH012612590000~~2F75762977,imi:5e7f202fe5eb76a2aed5c2241c418e0593a1b330","date":"","icon":"https:\/\/staticqbr-nl-prod.prod.cdn.dmdsdp.com\/image-service\/ImagesEPG\/EventImages\/p196625_b_v7_am.jpg","description":"Viewers get to ride along with a team of highly-trained professionals from California's San Fernando Valley as they repossess cars ... no matter how angry the owners may get. The stories depicted are based on real events.","category":"Reality"},"10605558":{"channel":"lgi-nl-prod-master:NL_000066_019291","start":"1627400400","end":"1627401900","first":"O","idtitle":"OPERATIONREPO","title":"Operation Repo","program_id":"crid:~~2F~~2Fgn.tv~~2F196625~~2FSH012612590000~~2F75762978,imi:283f7aa0d1ad056045b9933cac778403201157be","date":"","icon":"https:\/\/staticqbr-nl-prod.prod.cdn.dmdsdp.com\/image-service\/ImagesEPG\/EventImages\/p196625_b_v7_am.jpg","description":"Viewers get to ride along with a team of highly-trained professionals from California's San Fernando Valley as they repossess cars ... no matter how angry the owners may get. The stories depicted are based on real events.","category":"Reality"},"10605701":{"channel":"lgi-nl-prod-master:NL_000066_019291","start":"1627401900","end":"1627404900","first":"E","idtitle":"EXTREMESALVAGESQUAD","title":"Extreme Salvage Squad","program_id":"crid:~~2F~~2Fgn.tv~~2F15897481~~2FEP032189780005,imi:8e64313b37d6e894efbb3815fa47b232fbb48ed7","date":"2019","icon":"https:\/\/staticqbr-nl-prod.prod.cdn.dmdsdp.com\/image-service\/ImagesEPG\/EventImages\/p15774214_b_v11_ad.jpg","description":"The team head out during low tide to attempt the removal of a damaged pontoon, starting by pumping out the sand that is weighing it down.","category":"Reality, Documentaire"},"10606384":{"channel":"lgi-nl-prod-master:NL_000066_019291","start":"1627404900","end":"1627406400","first":"J","idtitle":"JUDGEJUDY","title":"Judge Judy","program_id":"crid:~~2F~~2Fgn.tv~~2F10002688~~2FEP012603132192,imi:da5e04f2c492c4bb5d4037bb0f6917d7050a15dc","date":"2013","icon":"https:\/\/staticqbr-nl-prod.prod.cdn.dmdsdp.com\/image-service\/ImagesEPG\/EventImages\/p9442556_b_v12_aa.jpg","description":"A plaintiff regrets helping out his daughter and son-in-law, who resist paying off their debt.","category":"Reality, Recht"},"10607262":{"channel":"lgi-nl-prod-master:NL_000066_019291","start":"1627406400","end":"1627407900","first":"J","idtitle":"JUDGEJUDY","title":"Judge Judy","program_id":"crid:~~2F~~2Fgn.tv~~2F9988720~~2FEP012603132193,imi:9330a21ffc9479a73613ba35668ff111ba0dc175","date":"2013","icon":"https:\/\/staticqbr-nl-prod.prod.cdn.dmdsdp.com\/image-service\/ImagesEPG\/EventImages\/p9442556_b_v12_aa.jpg","description":"A landlord says a couple with seven children and two animals left a house in shambles.","category":"Reality, Recht"},"10607369":{"channel":"lgi-nl-prod-master:NL_000066_019291","start":"1627407900","end":"1627409400","first":"J","idtitle":"JUDGEJUDY","title":"Judge Judy","program_id":"crid:~~2F~~2Fgn.tv~~2F9988718~~2FEP012603132194,imi:88b87fd0c61a9e37da66b8cee1a10c7ebc7ce3d3","date":"2013","icon":"https:\/\/staticqbr-nl-prod.prod.cdn.dmdsdp.com\/image-service\/ImagesEPG\/EventImages\/p9442556_b_v12_aa.jpg","description":"Accusations of breaking a lease; a 6-year-old denies crashing into a moving truck with his bicycle.","category":"Reality, Recht"},"10607488":{"channel":"lgi-nl-prod-master:NL_000066_019291","start":"1627409400","end":"1627412400","first":"S","idtitle":"SOMETHINGSKILLINGME","title":"Something's Killing Me","program_id":"crid:~~2F~~2Fgn.tv~~2F17462356~~2FEP030640520017,imi:9df3ec737b8ac2d253feb5ed12160660ead22477","date":"2019","icon":"https:\/\/staticqbr-nl-prod.prod.cdn.dmdsdp.com\/image-service\/ImagesEPG\/EventImages\/p17462817_b_v12_aa.jpg","description":"Several doctors and CDC authorities spend months trying to figure out what California honeymooners, a surfer in Hawaii and a toddler in Tennessee have in common.","category":"Documentaire, Medisch, Gezondheid"},"10608433":{"channel":"lgi-nl-prod-master:NL_000066_019291","start":"1627412400","end":"1627415400","first":"W","idtitle":"WORLDSMOSTEVILKILLERS","title":"World's Most Evil Killers","program_id":"crid:~~2F~~2Fgn.tv~~2F18012126~~2FEP026904340044,imi:e039b573f75577f04e7394047686309b72f839d2","date":"2020","icon":"https:\/\/staticqbr-nl-prod.prod.cdn.dmdsdp.com\/image-service\/ImagesEPG\/EventImages\/p17233730_b_v12_aa.jpg","description":"Delving into the horrific serial killer Harold Shipman, a trusted GP who murdered at least 215 people, and was found guilty for the murder of 15.","category":"Documentaire, Misdaad"},"10609371":{"channel":"lgi-nl-prod-master:NL_000066_019291","start":"1627415400","end":"1627418400","first":"C","idtitle":"CHEATERS","title":"Cheaters","program_id":"crid:~~2F~~2Fgn.tv~~2F2435950~~2FEP012731240314,imi:38e0b28e6d5eed917ba1d8db34629aa77a954c61","date":"2008","icon":"https:\/\/staticqbr-nl-prod.prod.cdn.dmdsdp.com\/image-service\/ImagesEPG\/EventImages\/p185490_b_v8_aj.jpg","description":"Ray wonders whether his girlfriend turned down his proposal because her heart lies elsewhere. Rachel finds texts from another woman on her partner's phone.","category":"Reality"},"10610341":{"channel":"lgi-nl-prod-master:NL_000066_019291","start":"1627418400","end":"1627421400","first":"W","idtitle":"WIVESWITHKNIVES","title":"Wives With Knives","program_id":"crid:~~2F~~2Fgn.tv~~2F12273902~~2FEP017191740030,imi:0d9de7928166948a1b3e78e8e8cd537a1ed50e0b","date":"2015","icon":"https:\/\/staticqbr-nl-prod.prod.cdn.dmdsdp.com\/image-service\/ImagesEPG\/EventImages\/p12199755_b_v8_aa.jpg","description":"Transgender woman Terri Pearson is forced to fight for her life after finding romance with a man who abuses her.","category":"Documentaire, Misdaad"},"10611304":{"channel":"lgi-nl-prod-master:NL_000066_019291","start":"1627421400","end":"1627424700","first":"P","idtitle":"PARANORMALSURVIVOR","title":"Paranormal Survivor","program_id":"crid:~~2F~~2Fgn.tv~~2F16712257~~2FEP023540500034,imi:a1810b02b6aa7ba65f49a6e4c5116b6165c7fcc0","date":"2019","icon":"https:\/\/staticqbr-nl-prod.prod.cdn.dmdsdp.com\/image-service\/ImagesEPG\/EventImages\/p16710926_b_v12_aa.jpg","description":"Monica shares her experiences being stalked by the Grim Reaper; Brittany shares her experiences of torment. A mother and her two daughters share their experiences with an evil lizard-man.","category":"Docudrama, Paranormaal"}}