{"55719":{"channel":"141431430","start":"1672534800","end":"1672536600","title":"Brickies","program_id":"1312561363","date":"","icon":"https:\/\/t-mobiletv.nl:443\/CPS\/images\/universal\/film\/program\/202212\/20221224\/21\/202212240201019490wb.jpg","description":"","category":""},"55720":{"channel":"141431430","start":"1672536600","end":"1672538400","title":"Brickies","program_id":"1312561369","date":"","icon":"https:\/\/t-mobiletv.nl:443\/CPS\/images\/universal\/film\/program\/202212\/20221224\/29\/20221224020101949h0j.jpg","description":"","category":""},"55721":{"channel":"141431430","start":"1672538400","end":"1672540200","title":"Brickies","program_id":"1312561375","date":"","icon":"https:\/\/t-mobiletv.nl:443\/CPS\/images\/universal\/film\/program\/202212\/20221224\/53\/20221224020101950mmr.jpg","description":"","category":""},"55722":{"channel":"141431430","start":"1672540200","end":"1672542000","title":"Brickies","program_id":"1312561381","date":"","icon":"https:\/\/t-mobiletv.nl:443\/CPS\/images\/universal\/film\/program\/202212\/20221224\/59\/2022122402010195047w.jpg","description":"","category":""},"55723":{"channel":"141431430","start":"1672542000","end":"1672543800","title":"Brickies","program_id":"1312561387","date":"","icon":"https:\/\/t-mobiletv.nl:443\/CPS\/images\/universal\/film\/program\/202212\/20221224\/4\/20221224020101950uqa.jpg","description":"","category":""},"55724":{"channel":"141431430","start":"1672543800","end":"1672545600","title":"Brickies","program_id":"1312561393","date":"","icon":"https:\/\/t-mobiletv.nl:443\/CPS\/images\/universal\/film\/program\/202212\/20221224\/21\/20221224020101950xtl.jpg","description":"","category":""}}