{"2287":{"channel":"boW4lYH6CESbHzgZais_lQAAAAc","start":"1626519600","end":"1626521400","title":"MotorNL TV","program_id":"721B1BC228C1FF3C460C667A8DE153C3","date":"2021","icon":"https:\/\/images.nlziet.nl\/metadataimportimages\/source\/D9AD45090ECCE41F145BB71AE06DCD0273B711984E87E2C807EFF15515E05917.jpg","description":"Informatief programma voor motorliefhebbers dat boordevol inspiratie, motortests en informatie over producten zit.","category":"Motors"},"16374":{"channel":"boW4lYH6CESbHzgZais_lQAAAAc","start":"1627124400","end":"1627126260","title":"MotorNL TV","program_id":"872EC7F798A2C9D22A17D252C7AF5EA0","date":"2021","icon":"https:\/\/images.nlziet.nl\/metadataimportimages\/source\/D9AD45090ECCE41F145BB71AE06DCD0273B711984E87E2C807EFF15515E05917.jpg","description":"Informatief programma voor motorliefhebbers dat boordevol inspiratie, motortests en informatie over producten zit.","category":"Motors"}}